drf_microservice_auth/__init__.py
drf_microservice_auth/admin.py
drf_microservice_auth/apps.py
drf_microservice_auth/authentication.py
drf_microservice_auth/migrations/0001_initial.py
drf_microservice_auth/migrations/__init__.py
drf_microservice_auth/mixins.py
drf_microservice_auth/models.py
drf_microservice_auth/serializers.py
drf_microservice_auth/tests.py
drf_microservice_auth/urls.py
drf_microservice_auth/views.py
drf_microservice_auth-0.1.0.dist-info/WHEEL
drf_microservice_auth-0.1.0.dist-info/METADATA
drf_microservice_auth-0.1.0.dist-info/RECORD
