Metadata-Version: 2.1
Name: drf-microservice-auth
Version: 0.1.0
Summary: 
Author: christian
Author-email: imchristianlowe@gmail.com
Requires-Python: >=3.9,<4.0
Classifier: Programming Language :: Python :: 3
Classifier: Programming Language :: Python :: 3.9
Classifier: Programming Language :: Python :: 3.10
Classifier: Programming Language :: Python :: 3.11
Requires-Dist: cryptography (>=39.0.1,<40.0.0)
Requires-Dist: django (>=4.1.6,<5.0.0)
Requires-Dist: djangorestframework (>=3.14.0,<4.0.0)
Requires-Dist: pyjwt (>=2.6.0,<3.0.0)
